forecasting_tools/__init__.py
forecasting_tools/agents_and_tools/__init__.py
forecasting_tools/agents_and_tools/ai_congress/__init__.py
forecasting_tools/agents_and_tools/ai_congress/congress_member_agent.py
forecasting_tools/agents_and_tools/ai_congress/congress_orchestrator.py
forecasting_tools/agents_and_tools/ai_congress/data_models.py
forecasting_tools/agents_and_tools/ai_congress/member_profiles.py
forecasting_tools/agents_and_tools/base_rates/base_rate_researcher.py
forecasting_tools/agents_and_tools/base_rates/deduplicator.py
forecasting_tools/agents_and_tools/base_rates/estimator.py
forecasting_tools/agents_and_tools/base_rates/niche_list_researcher.py
forecasting_tools/agents_and_tools/deprecated/configured_llms.py
forecasting_tools/agents_and_tools/deprecated/general_researcher.py
forecasting_tools/agents_and_tools/deprecated/question_generator.py
forecasting_tools/agents_and_tools/deprecated/question_responder.py
forecasting_tools/agents_and_tools/deprecated/question_router.py
forecasting_tools/agents_and_tools/deprecated/research_coordinator.py
forecasting_tools/agents_and_tools/minor_tools.py
forecasting_tools/agents_and_tools/other/data_analyzer.py
forecasting_tools/agents_and_tools/other/hosted_file.py
forecasting_tools/agents_and_tools/question_generators/generated_question.py
forecasting_tools/agents_and_tools/question_generators/harmful_question_identifier.py
forecasting_tools/agents_and_tools/question_generators/q3_q4_quarterly_questions.json
forecasting_tools/agents_and_tools/question_generators/question_decomposer.py
forecasting_tools/agents_and_tools/question_generators/question_operationalizer.py
forecasting_tools/agents_and_tools/question_generators/simple_question.py
forecasting_tools/agents_and_tools/question_generators/topic_generator.py
forecasting_tools/agents_and_tools/research/computer_use.py
forecasting_tools/agents_and_tools/research/find_a_dataset.py
forecasting_tools/agents_and_tools/research/key_factors_researcher.py
forecasting_tools-0.2.85.dist-info/METADATA
forecasting_tools-0.2.85.dist-info/WHEEL
forecasting_tools-0.2.85.dist-info/licenses/LICENSE
forecasting_tools-0.2.85.dist-info/RECORD
