Metadata-Version: 2.4
Name: forecasting-tools
Version: 0.2.85
Summary: AI forecasting and research tools to help humans reason about and forecast the future
License: MIT
License-File: LICENSE
Keywords: ai,forecasting,research,metaculus,prediction,future,market
Author: Benjamin Wilson
Author-email: mokoresearch@gmail.com
Requires-Python: >=3.11,<4.0
Classifier: Development Status :: 4 - Beta
Classifier: Intended Audience :: Science/Research
Classifier: License :: OSI Approved :: MIT License
Classifier: Natural Language :: English
Classifier: Operating System :: OS Independent
Classifier: Programming Language :: Python :: 3
Classifier: Programming Language :: Python :: 3.11
Classifier: Programming Language :: Python :: 3.12
Classifier: Programming Language :: Python :: 3.13
Classifier: Programming Language :: Python :: 3.14
Classifier: Topic :: Scientific/Engineering :: Artificial Intelligence
Requires-Dist: aiofiles (>=24.1.0,<26.0.0)
Requires-Dist: aiohttp (>=3.9.3,<4.0.0)
Requires-Dist: aiolimiter (>=1.1.0,<2.0.0)
Requires-Dist: asknews (>=0.9.1,<0.14.0)
Requires-Dist: asyncio (>=3.0.0,<5.0.0)
Requires-Dist: exceptiongroup (>=1.2.2,<2.0.0)
Requires-Dist: faker (>=37.0.0,<39.0.0)
Requires-Dist: hyperbrowser (>=0.53.0,<0.76.0)
Requires-Dist: litellm (>=1.59.1,!=1.76.*,!=1.77.*)
Requires-Dist: nest-asyncio (>=1.5.8,<2.0.0)
Requires-Dist: numpy (>=1.26.0,<3.0.0)
Requires-Dist: openai (>=1.51.0,<3.0.0)
Requires-Dist: openai-agents[litellm] (>=0.2.0,<0.7.0)
Requires-Dist: pandas (>=2.2.3,<3.0.0)
Requires-Dist: pendulum (>=3.1.0,<4.0.0)
Requires-Dist: pillow (>=9.0.0,<12.0.0)
Requires-Dist: plotly (>=5.24.1,<7.0.0)
Requires-Dist: pydantic (>=2.9.2,<3.0.0)
Requires-Dist: python-dotenv (>=1.0.0,<2.0.0)
Requires-Dist: regex (>=2024.11.6,<2026.0.0)
Requires-Dist: requests (>=2.32.3,<3.0.0)
Requires-Dist: scikit-learn (>=1.5.2,<2.0.0)
Requires-Dist: streamlit (>=1.20.0,<2.0.0)
Requires-Dist: tenacity (>=8.0.0,<10.0.0)
Requires-Dist: tiktoken (>=0.8.0,<0.13.0)
Requires-Dist: typeguard (>=4.3.0,<5.0.0)
Requires-Dist: unidecode (>=1.4.0,<2.0.0)
Project-URL: Repository, https://github.com/Metaculus/forecasting-tools
